{"cameraMode":{"drawMode":0,"name":"Shaded","section":"Shading Mode"},"sceneLighting":true,"audioPlay":false,"sceneViewState":{"showFog":true,"showMaterialUpdate":false,"showSkybox":true,"showFlares":true,"showImageEffects":true,"showParticleSystems":true},"in2DMode":false,"pivot":{"x":1.318298101425171,"y":1.0766767263412476,"z":4.566131591796875},"rotation":{"x":0.00027888486511074007,"y":-0.9994558095932007,"z":0.03180887922644615,"w":0.008730239234864712},"size":0.43737900257110598,"orthographic":false}